easypreprocessing.py
easypreprocessing-1.0.7.data/scripts/easypreprocessing.py
easypreprocessing-1.0.7.dist-info/LICENCE.txt
easypreprocessing-1.0.7.dist-info/METADATA
easypreprocessing-1.0.7.dist-info/WHEEL
easypreprocessing-1.0.7.dist-info/entry_points.txt
easypreprocessing-1.0.7.dist-info/top_level.txt
easypreprocessing-1.0.7.dist-info/RECORD
