Metadata-Version: 2.1
Name: easypreprocessing
Version: 1.0.7
Summary: An easy to use pre-processing utility for machine learning.
Home-page: UNKNOWN
Author: Shreyas Kudav
Author-email: shreyaskudav@gmail.com
License: MIT
Keywords: machine learning
Platform: UNKNOWN
Classifier: Development Status :: 1 - Planning
Classifier: Intended Audience :: Developers
Classifier: Operating System :: Microsoft :: Windows :: Windows 10
Classifier: License :: OSI Approved :: MIT License
Classifier: Programming Language :: Python :: 3
License-File: LICENCE.txt
Requires-Dist: numpy
Requires-Dist: pandas
Requires-Dist: seaborn
Requires-Dist: sklearn
Requires-Dist: kneed
Requires-Dist: imbalanced-learn
